setup.py
akcli/__init__.py
akcli/cli.py
akcli/dns.py
akcli.egg-info/PKG-INFO
akcli.egg-info/SOURCES.txt
akcli.egg-info/dependency_links.txt
akcli.egg-info/requires.txt
akcli.egg-info/top_level.txt
bin/akcli