Metadata-Version: 1.0
Name: akcli
Version: 0.1.3
Summary: Akamai CLI tool written in Python
Home-page: https://github.com/iamseth/akcli
Author: Seth Miller
Author-email: seth@sethmiller.me
License: UNKNOWN
Keywords: akamai,dns,cli,client
Platform: UNKNOWN
